micromenu.py
tests/__init__.py
tests/test_micromenu.py
micromenu-2.0.3.dist-info/LICENSE
micromenu-2.0.3.dist-info/METADATA
micromenu-2.0.3.dist-info/WHEEL
micromenu-2.0.3.dist-info/top_level.txt
micromenu-2.0.3.dist-info/RECORD
