Metadata-Version: 2.1
Name: micromenu
Version: 2.0.3
Summary: A minimalistic command line menu
Home-page: https://github.com/andli/micromenu
Author: Andreas Ehrlund
Author-email: a.ehrlund@gmail.com
License: UNKNOWN
Platform: UNKNOWN
Classifier: Programming Language :: Python :: 3
Classifier: License :: OSI Approved :: MIT License
Classifier: Operating System :: OS Independent
Provides-Extra: dev
Requires-Dist: wheel ; extra == 'dev'
Requires-Dist: pytest ; extra == 'dev'
Requires-Dist: mock ; extra == 'dev'
Requires-Dist: pytest-cov ; extra == 'dev'
